s3_sign-0.2.dist-info/metadata.json
s3_sign-0.2.dist-info/METADATA
s3_sign-0.2.dist-info/WHEEL
s3_sign-0.2.dist-info/top_level.txt
s3_sign-0.2.dist-info/DESCRIPTION.rst
s3_sign-0.2.dist-info/RECORD
s3sign/__init__.py
s3sign/__main__.py
s3_sign-0.2.data/scripts/s3-sign
