Metadata-Version: 2.0
Name: s3-sign
Version: 0.2
Summary: Generates pre-signed URLs for S3.
Home-page: https://github.com/BashtonLtd/s3-sign
Author: Raymond Butcher
Author-email: ray@bashton.com
License: Apache License 2.0
Platform: UNKNOWN
Requires-Dist: boto3
Requires-Dist: requests
